sliceplots/__init__.py
sliceplots/one_dimensional.py
sliceplots/two_dimensional.py
sliceplots/util.py
sliceplots-0.3.3.dist-info/AUTHORS.rst
sliceplots-0.3.3.dist-info/LICENSE
sliceplots-0.3.3.dist-info/METADATA
sliceplots-0.3.3.dist-info/WHEEL
sliceplots-0.3.3.dist-info/top_level.txt
sliceplots-0.3.3.dist-info/RECORD
