Metadata-Version: 2.1
Name: sliceplots
Version: 0.3.3
Summary: thin wrapper on top of matplotlib's imshow for 2D plotting with attached slice plots
Home-page: https://github.com/berceanu/sliceplots
Author: Andrei Berceanu
Author-email: andreicberceanu@gmail.com
License: BSD license
Keywords: slice plot plotting
Classifier: Development Status :: 4 - Beta
Classifier: Intended Audience :: Science/Research
Classifier: License :: OSI Approved :: BSD License
Classifier: Natural Language :: English
Classifier: Topic :: Scientific/Engineering :: Physics
Classifier: Programming Language :: Python :: 3.6
Requires-Python: >= 3.6
License-File: LICENSE
License-File: AUTHORS.rst
Requires-Dist: matplotlib >=3.1.0
